autospectra/__init__.py
autospectra/models.py
autospectra/preprocessing.py
autospectra-0.1.0.dist-info/LICENSE
autospectra-0.1.0.dist-info/METADATA
autospectra-0.1.0.dist-info/WHEEL
autospectra-0.1.0.dist-info/top_level.txt
autospectra-0.1.0.dist-info/zip-safe
autospectra-0.1.0.dist-info/RECORD
