Metadata-Version: 2.1
Name: autospectra
Version: 0.1.0
Summary: Automated spectroscopic modelling
Home-page: https://github.com/zefang-shen/autospectra.git
Author: Zefang
Author-email: zefang2455@gmail.com
License: MIT
Platform: UNKNOWN
Classifier: License :: OSI Approved :: MIT License
Classifier: Programming Language :: Python :: 3
Requires-Dist: optuna
Requires-Dist: numpy
Requires-Dist: pandas
